geomcompare/__init__.py
geomcompare/_geomrefdb_abc.py
geomcompare/_misc.py
geomcompare/comparefunc.py
geomcompare/geomrefdb.py
geomcompare/geomutils.py
geomcompare/io.py
geomcompare/stats.py
geomcompare-0.3.0.dist-info/AUTHORS.rst
geomcompare-0.3.0.dist-info/LICENSE.rst
geomcompare-0.3.0.dist-info/METADATA
geomcompare-0.3.0.dist-info/WHEEL
geomcompare-0.3.0.dist-info/top_level.txt
geomcompare-0.3.0.dist-info/RECORD
