Metadata-Version: 2.1
Name: geomcompare
Version: 0.3.0
Summary: Compare two sets of geometrical features.
Home-page: https://geomcompare.readthedocs.io/en/latest/index.html
Author: Mathieu Tachon
Author-email: tachon.mathieu@protonmail.com
License: GPL-3.0-or-later
Platform: any
Classifier: License :: OSI Approved :: GNU General Public License v3 or later (GPLv3+)
Classifier: Programming Language :: Python :: 3
Classifier: Programming Language :: Python :: 3.9
Requires-Python: >=3.9
License-File: LICENSE.rst
License-File: AUTHORS.rst
Requires-Dist: shapely
Requires-Dist: pyproj
Requires-Dist: psycopg2
Requires-Dist: rtree
Requires-Dist: numpy
Provides-Extra: testing
Requires-Dist: setuptools ; extra == 'testing'
Requires-Dist: pytest ; extra == 'testing'
Requires-Dist: pytest-cov ; extra == 'testing'
